CarDEC/CarDEC_API.py
CarDEC/CarDEC_MainModel.py
CarDEC/CarDEC_SAE.py
CarDEC/CarDEC_count_decoder.py
CarDEC/CarDEC_dataloaders.py
CarDEC/CarDEC_layers.py
CarDEC/CarDEC_optimization.py
CarDEC/CarDEC_utils.py
CarDEC/__init__.py
cardec-1.0.3.dist-info/LICENSE.rtf
cardec-1.0.3.dist-info/METADATA
cardec-1.0.3.dist-info/WHEEL
cardec-1.0.3.dist-info/top_level.txt
cardec-1.0.3.dist-info/RECORD
