Metadata-Version: 2.1
Name: cardec
Version: 1.0.3
Summary: A deep learning method for joint batch correction, denoting, and clustering of single-cell rna-seq data.
Home-page: https://github.com/jlakkis/CarDEC
Author: Justin Lakkis
Author-email: jlakks@gmail.com
License: UNKNOWN
Platform: UNKNOWN
Classifier: Programming Language :: Python :: 3
Classifier: License :: OSI Approved :: MIT License
Classifier: Operating System :: OS Independent
Requires-Python: >=3.7
Requires-Dist: numpy (>=1.18.1)
Requires-Dist: pandas (>=1.0.1)
Requires-Dist: scipy (>=1.4.1)
Requires-Dist: tensorflow (<=2.3.1,>=2.0.1)
Requires-Dist: scikit-learn (>=0.22.2.post1)
Requires-Dist: scanpy (>=1.5.1)
Requires-Dist: louvain (>=0.6.1)
